coloraide_extras/__init__.py
coloraide_extras/__meta__.py
coloraide_extras/everything.py
coloraide_extras/py.typed
coloraide_extras/contrast/__init__.py
coloraide_extras/contrast/contrast_michelson.py
coloraide_extras/contrast/contrast_weber.py
coloraide_extras/interpolate/__init__.py
coloraide_extras/interpolate/spectral.py
coloraide_extras/spaces/__init__.py
coloraide_extras/spaces/uvw.py
coloraide_extras-1.12.2.dist-info/METADATA
coloraide_extras-1.12.2.dist-info/WHEEL
coloraide_extras-1.12.2.dist-info/licenses/LICENSE.md
coloraide_extras-1.12.2.dist-info/RECORD
